{
  "id": "numberExam",
  "title": "Числовой тест",
  "description": "",
  "questions": [
  {
    "type": "radio",
    "title": "Какой процент составил развод к количеству браков в 2017 году?",
    "choices": ["32%", "21%", "26%", "38%", "42%"],
    "correctAnswer": "38%",
    "image": "1001"
  },
  {
    "type": "radio",
    "title": "Как изменилась разница между количеством браков и разводов в 2020 году по сравнению с 2017 годом?",
    "choices": ["выросла на 32%", "выросла на 25%", "выросла на 21%", "снизилась на 25%", "снизилась на 21%"],
    "correctAnswer": "выросла на 21%",
    "image": "1001"
  },
  {
    "type": "radio",
    "title": "Как изменилась разница между количеством браков и разводов в 2019 году по сравнению с 2018 годом?",
    "choices": ["выросла на 6%", "выросла на 14%", "выросла на 16%", "снизилась на 14%", "снизилась на 4%"],
    "correctAnswer": "снизилась на 4%",
    "image": "1001"
  },
  {
    "type": "radio",
    "title": "Как изменилась разница между количеством браков и разводов в 2020 году по сравнению с 2018 годом?",
    "choices": ["выросла на 6%", "выросла на 14%", "выросла на 16%", "снизилась на 14%", "снизилась на 4%"],
    "correctAnswer": "увеличилось на 28%",
    "image": "1001"
  },
  {
    "type": "radio",
    "title": "Сколько составило количество браков в 2021 году ко всему периоду:",
    "choices": ["7%", "10%", "15%", "20%", "26%"],
    "correctAnswer": "15%",
    "image": "1001"
  },
  {
    "type": "radio",
    "title": "Сколько составило количество разводов в 2019 году ко всему периоду:",
    "choices": ["7%", "10%", "15%", "20%", "24%"],
    "correctAnswer": "24%",
    "image": "1001"
  },
  {
    "type": "radio",
    "title": "Как изменилась разница между количеством браков и разводов в г. Алматы в 2023 году по сравнению с 2022 годом?",
    "choices": ["выросла на 6,4%", "выросла на 3,4%", "выросла на 4,4%", "снизилась на 4,4%", "снизилась на 1,4%"],
    "correctAnswer": "снизилась на 4,4%",
    "image": "1003"
  },
  {
    "type": "radio",
    "title": "Как изменилась разница между количеством браков и разводов в г. Костанай в 2023 году по сравнению с 2022 годом?",
    "choices": ["выросла на 15,5%", "выросла на 12,5%", "выросла на 5%", "снизилась на 7,5%", "снизилась на 6,5%"],
    "correctAnswer": "снизилась на 7,5%",
    "image": "1003"
  },
  {
    "type": "radio",
    "title": "Какой процент в 2023 году составил с компьютерными инцидентами составил Фишинг?",
    "choices": ["составил 10,1%", "составил 6%", "составил 2,2%", "составил 15%", "составил 8,2%"],
    "correctAnswer": "составил 8,2%",
    "image": "1005"
  },
  {
    "type": "radio",
    "title": "Какой процент в 2024 году составил инцидент -- Вредоносное ПО?",
    "choices": ["11%", "16%", "20%", "28%", "40%"],
    "correctAnswer": "28%",
    "image": "1005"
  },
  {
    "type": "radio",
    "title": "На сколько увеличилось общее количество инцидентов в 2024 году по сравнению с 2023 годом?",
    "choices": ["25%", "30%", "45%", "25%", "45%"],
    "correctAnswer": "увеличился на 45%",
    "image": "1005"
  },
  {
    "type": "radio",
    "title": "Как изменилась разница между количеством инцидентов связанных с Ботнетами в 2024 году по сравнению с 2023 годом?",
    "choices": ["выросла на 7,2%", "выросла на 6,9%", "выросла на 4,5%", "снизилась на 4,5%", "снизилась на 3,2%"],
    "correctAnswer": "снизилась на 6,9%",
    "image": "1005"
  },
  {
    "type": "radio",
    "title": "Как изменилась разница между количеством инцидентов связанных с Фишингом в 2024 году по сравнению с 2023 годом?",
    "choices": ["выросла на 7,35%", "выросла на 6,9%", "выросла на 4,55%", "снизилась на 4,35%", "снизилась на 7,35%"],
    "correctAnswer": "снизилась на 7,35%",
    "image": "1005"
  },
  {
    "type": "radio",
    "title": "Как изменилась разница между количеством инцидентов связанных с Вредоносными ПО в 2024 году по сравнению с 2023 годом?",
    "choices": ["увеличилась на 22%", "увеличилась на 32%", "увеличилась на 42%", "уменьшилась на 12%", "уменьшилась на 22%"],
    "correctAnswer": "увеличилась на 32%",
    "image": "1005"
  },
  {
    "type": "radio",
    "title": "Как изменился безвозвратный ущерб в 2023 году по сравнению с 2024 годом?",
    "choices": ["вырос на 44%", "вырос на 88%", "вырос на 55%", "снизился на 44%", "снизился на 88%"],
    "correctAnswer": "вырос на 88%",
    "image": "1007"
  },
  {
    "type": "radio",
    "title": "Как изменился установленный ущерб между 2023-2024 годом?",
    "choices": ["вырос на 63%", "вырос на 71%", "вырос на 46%", "снизился на 35%", "снизился на 50%"],
    "correctAnswer": "увеличился на 71%",
    "image": "1007"
  },
  {
    "type": "radio",
    "title": "Какую часть ущерба удалось вернуть в 2024 году?",
    "choices": ["11%", "21%", "15%", "19%", "22%"],
    "correctAnswer": "11%",
    "image": "1007"
  },
  {
    "type": "radio",
    "title": "Какую часть ущерба удалось вернуть в 2023 году?",
    "choices": ["11%", "21%", "15%", "19%", "22%"],
    "correctAnswer": "19%",
    "image": "1007"
  },
  {
    "type": "radio",
    "title": "Какую часть составили пары из села в 2024 году?",
    "choices": ["22%", "40%", "45%", "36%", "61%"],
    "correctAnswer": "36%",
    "image": "1009"
  },
  {
    "type": "radio",
    "title": "Какой процент составили пары из города в 2024 году?",
    "choices": ["35%", "40%", "45%", "58%", "64%"],
    "correctAnswer": "64%",
    "image": "1009"
  },
  {
    "type": "radio",
    "title": "Во сколько раз пар из города больше чем пар из сел в 2022?",
    "choices": ["больше в 2 раза", "больше в 3 раза", "больше в 4 раза", "больше в 5 раз", "больше в 6 раза"],
    "correctAnswer": "больше в 2 раза",
    "image": "1009"
  },
  {
    "type": "radio",
    "title": "Во сколько раз пар из города больше чем пар из сел в 2024?",
    "choices": ["больше в 1,33 раза", "больше в 1,5 раза", "больше в 1,76 раза", "больше в 2,6 раз", "больше в 3,1 раза"],
    "correctAnswer": "больше в 1,76 раза",
    "image": "1009"
  },
  {
    "type": "radio",
    "title": "Как изменилась разница между парами из сел и городов в 2024 году по сравнению с 2022 годом?",
    "choices": ["увеличилась в 1,1", "увеличилась в 1,31", "увеличилась в 1,52", "увеличилась в 2,1", "увеличилась в 2,54"],
    "correctAnswer": "увеличилась в 1,31",
    "image": "1009"
  },
  {
    "type": "radio",
    "title": "На сколько сократилось количество туристов между 2021-2022 годом",
    "choices": ["уменьшилось на 2,0", "уменьшилось на 1,3", "уменьшилось на 0,7", "уменьшилось на 0,2", "уменьшилось на 3,3"],
    "correctAnswer": "уменьшилось на 0,7",
    "image": "1011"
  },
  {
    "type": "radio",
    "title": "Как изменился поток туристов в 2021 в сравнении с 2024 годом?",
    "choices": ["вырос в 3,8 раза", "вырос в 4 раза", "вырос в 4,2 раза", "вырос в 4,6 раза", "вырос в 5 раз"],
    "correctAnswer": "вырос в 4,6 раза",
    "image": "1011"
  },
  {
    "type": "radio",
    "title": "Как изменился поток туристов в 2019 в сравнении с 2020 годом?",
    "choices": ["уменьшился на 4%", "уменьшился на 8%", "уменьшился на 10%", "уменьшился на 12%", "уменьшился на 14%"],
    "correctAnswer": "уменьшился на 4%",
    "image": "1011"
  },
  {
    "type": "radio",
    "title": "Общий процент от всего периода в 2024 году?",
    "choices": ["15%", "21%", "27%", "33%", "40%"],
    "correctAnswer": "27%",
    "image": "1011"
  },
  {
    "type": "radio",
    "title": "Общий процент от всего периода в 2021 году?",
    "choices": ["2,6%", "3,9%", "5,8%", "6,5%", "8%"],
    "correctAnswer": "5,8%",
    "image": "1011"
  },
  {
    "type": "radio",
    "title": "Между какими годами был резкий скачок?",
    "choices": ["2019-2020", "2020-2021", "2021-2022", "2022-2023", "2023-2024"],
    "correctAnswer": "2023-2024",
    "image": "1011"
  },
  {
    "type": "radio",
    "title": "Между какими годами был резкий спад?",
    "choices": ["2019-2020", "2020-2021", "2021-2022", "2022-2023", "2023-2024"],
    "correctAnswer": "2020-2021",
    "image": "1011"
  },
  {
    "type": "radio",
    "title": "Как изменилась миграция с 2019 по 2020 год?",
    "choices": ["снизилась на 25%", "снизилась на 45%", "снизилась на 55%", "снизилась на 35%"],
    "correctAnswer": "снизилась на 55%",
    "image": "1013"
  },
  {
    "type": "radio",
    "title": "Процент миграции в 2021 от всего периода?",
    "choices": ["12%", "15%", "18%", "21%"],
    "correctAnswer": "18%",
    "image": "1013"
  },
  {
    "type": "radio",
    "title": "Как изменилась миграция с 2021 по 2022 год?",
    "choices": ["увеличилась на 1 %", "увеличилась на 4 %", "увеличилась на 7 %", "увеличилась на 10 %"],
    "correctAnswer": "увеличилась на 4 %",
    "image": "1013"
  },
  {
    "type": "radio",
    "title": "Процент миграции в 2019 году от всего периода?",
    "choices": ["29%", "32%", "36%", "39%"],
    "correctAnswer": "36%",
    "image": "1013"
  },
  {
    "type": "radio",
    "title": "Сравнение миграции в 2022-2023 годах среди не казахского народа?",
    "choices": ["снизилась на 10%", "снизилась на 20%", "снизилась на 30%", "снизилась на 40%", "снизилась на 50%"],
    "correctAnswer": "снизилась на 50%",
    "image": "1013"
  },
  {
    "type": "radio",
    "title": "Как изменилась статистика мужского бесплодия среди мужчин в 2024 по сравнению с 2023 годом?",
    "choices": ["увеличилась на 2%", "увеличилась на 5%", "увеличилась на 7%", "увеличилась на 9%"],
    "correctAnswer": "увеличилась на 7%",
    "image": "1015"
  },
  {
    "type": "radio",
    "title": "Как изменилась статистика бесплодия среди женщин в 2024 по сравнению с 2023 годом?",
    "choices": ["увеличилась на 15%", "увеличилась на 23%", "увеличилась на 29%", "увеличилась на 30%"],
    "correctAnswer": "увеличилась на 23%",
    "image": "1015"
  },
  {
    "type": "radio",
    "title": "Какой процент составил прирост вкладов в банке Centercredit в 2024 году по сравнению с итогом 2023 года?",
    "choices": ["95%", "99%", "103%", "109%"],
    "correctAnswer": "103%",
    "image": "1017"
  },
  {
    "type": "radio",
    "title": "Самый большой процентный показатель роста 2024 года к итогу 2023 года?",
    "choices": ["у Bereke Bank", "у Centercredit", "у Jusan", "у Halyk", "y Kaspi"],
    "correctAnswer": "у Bereke Bank",
    "image": "1017"
  },
  {
    "type": "radio",
    "title": "Какой процентный прирост вкладов показал Jusan в 2024 году по сравнению с 2023 годом?",
    "choices": ["1%", "2%", "3%", "4%"],
    "correctAnswer": "2%",
    "image": "1017"
  },
  {
    "type": "radio",
    "title": "У какого банка в 2024 году зафиксирован самый большой отток вкладов по сравнению с итогом 2023 года?",
    "choices": ["у Bereke Bank", "у Centercredit", "у Jusan", "у Halyk", "y Kaspi"],
    "correctAnswer": "y Kaspi",
    "image": "1017"
  },
  {
    "type": "radio",
    "title": "Какую часть вложений составили у Halyk от общего объема в 2024 году?",
    "choices": ["46%", "54%", "58%", "61%"],
    "correctAnswer": "54%",
    "image": "1017"
  },
  {
    "type": "radio",
    "title": "Самое большое увеличение налогов в промежутке 2023-2024 годов?",
    "choices": ["31%", "34%", "37%", "40%"],
    "correctAnswer": "на 34%",
    "image": "1019"
  },
  {
    "type": "radio",
    "title": "Какую долю от общего объема налогов в 2024 году составили платежи ТОО Beeline?",
    "choices": ["15%", "20%", "25%", "30%"],
    "correctAnswer": "25%",
    "image": "1019"
  },
  {
    "type": "radio",
    "title": "На сколько процентов увеличились налоговые платежи АО Кселл в 2024 году по сравнению с итогом 2023 года?",
    "choices": ["увеличились на 24%", "увеличились на 28%", "увеличились на 32%", "увеличились на 36%"],
    "correctAnswer": "увеличились на 36%",
    "image": "1019"
  },
  {
    "type": "radio",
    "title": "На сколько процентов увеличились налоговые платежи ТОО NITEC в 2024 году по сравнению с итогом 2023 года?",
    "choices": ["упали на 5%", "упали на 9%", "упали на 10%", "упали на 11%"],
    "correctAnswer": "упали на 10%",
    "image": "1019"
  },
  {
    "type": "radio",
    "title": "Какой процент от общего объема мирового рынка видеоигр в 2025 году приходится на США?",
    "choices": ["15%", "21%", "24%", "29%"],
    "correctAnswer": "24%",
    "image": "1021"
  },
  {
    "type": "radio",
    "title": "Какой процент от общего объема мирового рынка видеоигр в 2025 году приходится на Канаду?",
    "choices": ["1%", "2%", "4%", "6%"],
    "correctAnswer": "2%",
    "image": "1021"
  },
  {
    "type": "radio",
    "title": "На сколько процентов Латинская Америка меньше в процентном соотношении, чем США?",
    "choices": ["на 22%", "на 27%", "на 32%", "на 37%"],
    "correctAnswer": "на 27%",
    "image": "1021"
  },
  {
    "type": "radio",
    "title": "Какая разница в нетто продажах между долларами и евро в 2024 году?",
    "choices": ["доллар больше в 4,8 раза", "доллар больше в 5,3 раза", "доллар больше в 6,1 раза", "доллар больше в 7,2 раза"],
    "correctAnswer": "больше в 7,2 раза",
    "image": "1023"
  }
],
  "time": 25,
  "passingScore": null,
  "questionsTotal": 25
}
